{
  "main": {
    "id": "8f03fd54fb9bcffb",
    "type": "split",
    "children": [
      {
        "id": "6ff497dd5ea7add5",
        "type": "tabs",
        "children": [
          {
            "id": "98f7a533fc73238a",
            "type": "leaf",
            "state": {
              "type": "markdown",
              "state": {
                "file": "1Семестр/Термины по истории-ОРГ/Модернизация.md",
                "mode": "source",
                "source": false
              }
            }
          }
        ]
      }
    ],
    "direction": "vertical"
  },
  "left": {
    "id": "dc7cda35ae4552e4",
    "type": "split",
    "children": [
      {
        "id": "7ca287626ad45b16",
        "type": "tabs",
        "children": [
          {
            "id": "bf891766bb4c3410",
            "type": "leaf",
            "state": {
              "type": "file-explorer",
              "state": {
                "sortOrder": "alphabetical"
              }
            }
          },
          {
            "id": "858fb357002a61e9",
            "type": "leaf",
            "state": {
              "type": "search",
              "state": {
                "query": "",
                "matchingCase": false,
                "explainSearch": false,
                "collapseAll": false,
                "extraContext": false,
                "sortOrder": "alphabetical"
              }
            }
          },
          {
            "id": "aef323fb2cbdc613",
            "type": "leaf",
            "state": {
              "type": "bookmarks",
              "state": {}
            }
          }
        ]
      }
    ],
    "direction": "horizontal",
    "width": 200
  },
  "right": {
    "id": "35c52bdf3f4648df",
    "type": "split",
    "children": [
      {
        "id": "5b56a4d1b6882100",
        "type": "tabs",
        "children": [
          {
            "id": "755229e0e392f0e5",
            "type": "leaf",
            "state": {
              "type": "backlink",
              "state": {
                "file": "1Семестр/Термины по истории-ОРГ/Модернизация.md",
                "collapseAll": false,
                "extraContext": false,
                "sortOrder": "alphabetical",
                "showSearch": false,
                "searchQuery": "",
                "backlinkCollapsed": false,
                "unlinkedCollapsed": true
              }
            }
          },
          {
            "id": "f84f0aa3fb044614",
            "type": "leaf",
            "state": {
              "type": "outgoing-link",
              "state": {
                "file": "1Семестр/Термины по истории-ОРГ/Модернизация.md",
                "linksCollapsed": false,
                "unlinkedCollapsed": true
              }
            }
          },
          {
            "id": "b9ff60ecaa5b9eb1",
            "type": "leaf",
            "state": {
              "type": "tag",
              "state": {
                "sortOrder": "frequency",
                "useHierarchy": true
              }
            }
          },
          {
            "id": "2ac1e5b2e4aac6e3",
            "type": "leaf",
            "state": {
              "type": "outline",
              "state": {
                "file": "1Семестр/Термины по истории-ОРГ/Модернизация.md"
              }
            }
          },
          {
            "id": "cee51f11bbc75595",
            "type": "leaf",
            "state": {
              "type": "copilot-chat-view",
              "state": {}
            }
          },
          {
            "id": "27f89e74d6403691",
            "type": "leaf",
            "state": {
              "type": "calendar",
              "state": {}
            }
          },
          {
            "id": "f599fa3212c0306b",
            "type": "leaf",
            "state": {
              "type": "advanced-tables-toolbar",
              "state": {}
            }
          }
        ],
        "currentTab": 6
      }
    ],
    "direction": "horizontal",
    "width": 200
  },
  "left-ribbon": {
    "hiddenItems": {
      "switcher:Меню быстрого перехода": false,
      "graph:Граф": false,
      "canvas:Создать новый холст": false,
      "daily-notes:Сегодняшняя заметка": false,
      "templates:Вставить шаблон": false,
      "command-palette:Открыть палитру команд": false,
      "audio-recorder:Начать/остановить запись": false,
      "table-editor-obsidian:Advanced Tables Toolbar": false
    }
  },
  "active": "98f7a533fc73238a",
  "lastOpenFiles": [
    "1Семестр/История/8лекция.md",
    "2Семестр/менеджмент/1 лекция.md",
    "2Семестр/История/2А+.md",
    "2Семестр/менеджмент",
    "2Семестр/История/1A +.md",
    "2Семестр/История/практика история",
    "Без названия 1.md",
    "2Семестр/Управление качеством программного обеспечения/1..md",
    "1Семестр/стандартизация/Лицензирование деятельности в сфере информатизации.md",
    "2Семестр/термины/Код-ревью.md",
    "2Семестр/термины/Спецификация требований.md",
    "2Семестр/термины",
    "1Семестр/Термины по истории-ОРГ/Нацизм.md",
    "2Семестр/Управление качеством программного обеспечения",
    "1Семестр/История/19лекция.md",
    "1Семестр/История/21лекция.md",
    "1Семестр/История/23лекция.md",
    "2Семестр/История",
    "1Семестр/История/2лекция.md",
    "1Семестр/История/3лекция.md",
    "1Семестр/История/22Лекция.md",
    "2Семестр",
    "1Семестр",
    "1Семестр/ОРГ/Последняя лекция.md",
    "1Семестр/История/10лекция.md",
    "1Семестр/История/5лекция.md",
    "1Семестр/Термины по истории-ОРГ/Левые.md",
    "1Семестр/Термины по истории-ОРГ/Правые.md",
    "1Семестр/Термины по истории-ОРГ/Империализм.md",
    "1Семестр/Термины по истории-ОРГ/Модернизация.md",
    "1Семестр/Термины по истории-ОРГ/смута.md",
    "1Семестр/История/12лекция.md",
    "1Семестр/История/9Лекция.md",
    "1Семестр/стандартизация",
    "1Семестр/ОРГ",
    "Recording 20231204143644.webm",
    "Без названия.canvas"
  ]
}